scriptAutomation/__init__.py
scriptAutomation/main.py
script_sandbox-1.0.0.dist-info/LICENSE
script_sandbox-1.0.0.dist-info/METADATA
script_sandbox-1.0.0.dist-info/WHEEL
script_sandbox-1.0.0.dist-info/entry_points.txt
script_sandbox-1.0.0.dist-info/top_level.txt
script_sandbox-1.0.0.dist-info/RECORD
